routesimilarity
