Metadata-Version: 2.1
Name: routesimilarity
Version: 0.14
Summary: Methods for similarity scoring between routes
Home-page: https://github.com/shkr/routesimilarity
Author: Shashank Shekhar
Author-email: shashank.f1@gmail.com
License: MIT
Download-URL: https://github.com/shkr/routesimilarity/archive/0.1.tar.gz
Keywords: route,similarity,hausdorff
Platform: UNKNOWN
Classifier: Development Status :: 5 - Production/Stable
Classifier: Intended Audience :: Science/Research
Classifier: Intended Audience :: Developers
Classifier: Programming Language :: Python :: 3
